AUTHORS.rst
CONTRIBUTING.rst
HISTORY.rst
LICENSE
MANIFEST.in
README.rst
setup.py
ekit/__init__.py
ekit/context.py
ekit/logger.py
ekit/paths.py
ekit.egg-info/PKG-INFO
ekit.egg-info/SOURCES.txt
ekit.egg-info/dependency_links.txt
ekit.egg-info/not-zip-safe
ekit.egg-info/requires.txt
ekit.egg-info/top_level.txt