Metadata-Version: 2.1
Name: ekit
Version: 0.2.4
Summary: Toolbox for the Non-Gaussian Statistics Framework (NGSF)
Home-page: https://cosmo-docs.phys.ethz.ch/ekit
Author: Dominik Zuercher
Author-email: dominikz@phys.ethz.ch
License: MIT License
Keywords: ekit
Platform: UNKNOWN
Classifier: Development Status :: 4 - Beta
Classifier: Intended Audience :: Science/Research
Classifier: Intended Audience :: Developers
Classifier: License :: OSI Approved :: MIT License
Classifier: Natural Language :: English
Classifier: Programming Language :: Python :: 3.10
License-File: LICENSE
License-File: AUTHORS.rst
